emptydrops/__init__.py
emptydrops/cell_calling.py
emptydrops/constants.py
emptydrops/feature_ref.py
emptydrops/h5_constants.py
emptydrops/matrix.py
emptydrops/sgt.py
emptydrops-0.0.5.dist-info/LICENSE
emptydrops-0.0.5.dist-info/METADATA
emptydrops-0.0.5.dist-info/WHEEL
emptydrops-0.0.5.dist-info/top_level.txt
emptydrops-0.0.5.dist-info/RECORD
