Metadata-Version: 2.1
Name: emptydrops
Version: 0.0.5
Summary: Python implementation of emptydrops() in CellRanger v3.0.2
Home-page: https://github.com/nh3/emptydrops
Author: nh3
Author-email: nh3@users.noreply.github.com
License: UNKNOWN
Platform: UNKNOWN
Classifier: Programming Language :: Python :: 3
Classifier: License :: OSI Approved :: MIT License
Classifier: Operating System :: OS Independent
Requires-Dist: h5py
Requires-Dist: lz4
Requires-Dist: pandas
Requires-Dist: scipy
